redcache_ai/__init__.py
redcache_ai/config.py
redcache_ai/core.py
redcache_ai/storage.py
redcache_ai/llm/__init__.py
redcache_ai/llm/base.py
redcache_ai/llm/openai_llm.py
redcache_ai-0.1.1.dist-info/LICENSE
redcache_ai-0.1.1.dist-info/METADATA
redcache_ai-0.1.1.dist-info/WHEEL
redcache_ai-0.1.1.dist-info/top_level.txt
redcache_ai-0.1.1.dist-info/RECORD
