Metadata-Version: 2.1
Name: redcache-ai
Version: 0.1.1
Summary: A memory framework for Large Language Models and Agents
Home-page: https://github.com/chisasaw/redcache-ai
Author: Warren Chisasa
Author-email: warrenchisasa@gmail.com
Classifier: Programming Language :: Python :: 3
Classifier: License :: OSI Approved :: Apache Software License
Classifier: Operating System :: OS Independent
Requires-Python: >=3.6
License-File: LICENSE
Requires-Dist: openai
Requires-Dist: scikit-learn
Requires-Dist: numpy
